tsmetric/__init__.py
tsmetric/length.py
tsmetric/temp.py
tsmetric-0.1.2.dist-info/METADATA
tsmetric-0.1.2.dist-info/WHEEL
tsmetric-0.1.2.dist-info/RECORD
